{"main":"{\"left\":{\"size\":240,\"currentIndex\":0,\"tabbars\":[{\"containerId\":\"search\",\"hidden\":false},{\"containerId\":\"explorer\",\"hidden\":false},{\"containerId\":\"scm_container\",\"hidden\":false},{\"containerId\":\"extensions\",\"hidden\":false},{\"containerId\":\"3\",\"hidden\":false},{\"containerId\":\"2\",\"hidden\":false},{\"containerId\":\"1\",\"hidden\":false}]},\"right\":{\"size\":395,\"currentIndex\":0,\"tabbars\":[{\"containerId\":\"simulator\",\"hidden\":false}]},\"bottom\":{\"size\":300,\"currentIndex\":0,\"tabbars\":[{\"containerId\":\"devtools\",\"hidden\":false}],\"collapsed\":true}}","view/scm_container":"{\"sections\":[{\"viewId\":\"scm_provider\",\"collapsed\":false,\"hidden\":true},{\"viewId\":\"scm\",\"collapsed\":false,\"hidden\":false}]}","storageVersion":"0.73.3"}